[{"n":["http://dhi-roma.it/A","http://dhi-roma.it/Aa","http://dhi-roma.it/Ac","http://dhi-roma.it/Ae","http://dhi-roma.it/B","http://dhi-roma.it/Ba","http://dhi-roma.it/Bd","http://dhi-roma.it/Be","http://dhi-roma.it/Bg"],"i":["http://dhi-roma.it/A","http://dhi-roma.it/Aa","http://dhi-roma.it/Ab","http://dhi-roma.it/Ac","http://dhi-roma.it/Ae","http://dhi-roma.it/B","http://dhi-roma.it/Ba","http://dhi-roma.it/Bb","http://dhi-roma.it/Bc","http://dhi-roma.it/Bd","http://dhi-roma.it/Be","http://dhi-roma.it/Bf","http://dhi-roma.it/Bg","http://dhi-roma.it/Bi","http://dhi-roma.it/C","http://dhi-roma.it/Ca","http://dhi-roma.it/Cb","http://dhi-roma.it/Cc"],"in":["http://dhi-roma.it/A","http://dhi-roma.it/Ba"],"enciclopedie":["http://dhi-roma.it/Aa"],"enciclopedi":["http://dhi-roma.it/Aa"],"encicloped":["http://dhi-roma.it/Aa"],"enciclope":["http://dhi-roma.it/Aa"],"enciclop":["http://dhi-roma.it/Aa"],"enciclo":["http://dhi-roma.it/Aa"],"encicl":["http://dhi-roma.it/Aa"],"encic":["http://dhi-roma.it/Aa"],"enci":["http://dhi-roma.it/Aa"],"enc":["http://dhi-roma.it/Aa"],"en":["http://dhi-roma.it/Aa","http://dhi-roma.it/Ae","http://dhi-roma.it/B","http://dhi-roma.it/Be"],"e":["http://dhi-roma.it/Aa","http://dhi-roma.it/Ab","http://dhi-roma.it/Ac","http://dhi-roma.it/Ae","http://dhi-roma.it/B","http://dhi-roma.it/Be","http://dhi-roma.it/Bi","http://dhi-roma.it/Bk"],"nciclopedie":["http://dhi-roma.it/Aa"],"nciclopedi":["http://dhi-roma.it/Aa"],"ncicloped":["http://dhi-roma.it/Aa"],"nciclope":["http://dhi-roma.it/Aa"],"nciclop":["http://dhi-roma.it/Aa"],"nciclo":["http://dhi-roma.it/Aa"],"ncicl":["http://dhi-roma.it/Aa"],"ncic":["http://dhi-roma.it/Aa"],"nci":["http://dhi-roma.it/Aa"],"nc":["http://dhi-roma.it/Aa"],"ciclopedie":["http://dhi-roma.it/Aa"],"ciclopedi":["http://dhi-roma.it/Aa"],"cicloped":["http://dhi-roma.it/Aa"],"ciclope":["http://dhi-roma.it/Aa"],"ciclop":["http://dhi-roma.it/Aa"],"ciclo":["http://dhi-roma.it/Aa"],"cicl":["http://dhi-roma.it/Aa"],"cic":["http://dhi-roma.it/Aa"],"ci":["http://dhi-roma.it/Aa","http://dhi-roma.it/B"],"c":["http://dhi-roma.it/Aa","http://dhi-roma.it/Ac","http://dhi-roma.it/Ae","http://dhi-roma.it/B","http://dhi-roma.it/Ba","http://dhi-roma.it/Bb","http://dhi-roma.it/Bc","http://dhi-roma.it/Bd","http://dhi-roma.it/Bf","http://dhi-roma.it/Bg","http://dhi-roma.it/C","http://dhi-roma.it/Ca","http://dhi-roma.it/Cb","http://dhi-roma.it/Cc"],"iclopedie":["http://dhi-roma.it/Aa"],"iclopedi":["http://dhi-roma.it/Aa"],"icloped":["http://dhi-roma.it/Aa"],"iclope":["http://dhi-roma.it/Aa"],"iclop":["http://dhi-roma.it/Aa"],"iclo":["http://dhi-roma.it/Aa"],"icl":["http://dhi-roma.it/Aa"],"ic":["http://dhi-roma.it/Aa","http://dhi-roma.it/Ba","http://dhi-roma.it/Bc","http://dhi-roma.it/Bf","http://dhi-roma.it/Bg"],"clopedie":["http://dhi-roma.it/Aa"],"clopedi":["http://dhi-roma.it/Aa"],"cloped":["http://dhi-roma.it/Aa"],"clope":["http://dhi-roma.it/Aa"],"clop":["http://dhi-roma.it/Aa"],"clo":["http://dhi-roma.it/Aa"],"cl":["http://dhi-roma.it/Aa"],"lopedie":["http://dhi-roma.it/Aa"],"lopedi":["http://dhi-roma.it/Aa"],"loped":["http://dhi-roma.it/Aa"],"lope":["http://dhi-roma.it/Aa"],"lop":["http://dhi-roma.it/Aa"],"lo":["http://dhi-roma.it/Aa","http://dhi-roma.it/Bc","http://dhi-roma.it/Bd","http://dhi-roma.it/Be"],"l":["http://dhi-roma.it/Aa","http://dhi-roma.it/Ab","http://dhi-roma.it/Ac","http://dhi-roma.it/Ba","http://dhi-roma.it/Bc","http://dhi-roma.it/Bd","http://dhi-roma.it/Be","http://dhi-roma.it/Bf","http://dhi-roma.it/Cb"],"opedie":["http://dhi-roma.it/Aa"],"opedi":["http://dhi-roma.it/Aa"],"oped":["http://dhi-roma.it/Aa"],"ope":["http://dhi-roma.it/Aa"],"op":["http://dhi-roma.it/Aa"],"o":["http://dhi-roma.it/Aa","http://dhi-roma.it/Ab","http://dhi-roma.it/Bc","http://dhi-roma.it/Bd","http://dhi-roma.it/Be","http://dhi-roma.it/Bi","http://dhi-roma.it/Bk"],"pedie":["http://dhi-roma.it/Aa"],"pedi":["http://dhi-roma.it/Aa"],"ped":["http://dhi-roma.it/Aa"],"pe":["http://dhi-roma.it/Aa"],"p":["http://dhi-roma.it/Aa","http://dhi-roma.it/Bc"],"edie":["http://dhi-roma.it/Aa"],"edi":["http://dhi-roma.it/Aa"],"ed":["http://dhi-roma.it/Aa"],"die":["http://dhi-roma.it/Aa"],"di":["http://dhi-roma.it/Aa","http://dhi-roma.it/Bc","http://dhi-roma.it/Bf"],"d":["http://dhi-roma.it/Aa","http://dhi-roma.it/Bc","http://dhi-roma.it/Bf","http://dhi-roma.it/Bk"],"ie":["http://dhi-roma.it/Aa","http://dhi-roma.it/Ab","http://dhi-roma.it/B"],"bibliografie":["http://dhi-roma.it/Ab"],"bibliografi":["http://dhi-roma.it/Ab"],"bibliograf":["http://dhi-roma.it/Ab"],"bibliogra":["http://dhi-roma.it/Ab"],"bibliogr":["http://dhi-roma.it/Ab"],"bibliog":["http://dhi-roma.it/Ab"],"biblio":["http://dhi-roma.it/Ab"],"bibli":["http://dhi-roma.it/Ab"],"bibl":["http://dhi-roma.it/Ab"],"bib":["http://dhi-roma.it/Ab"],"bi":["http://dhi-roma.it/Ab"],"b":["http://dhi-roma.it/Ab"],"ibliografie":["http://dhi-roma.it/Ab"],"ibliografi":["http://dhi-roma.it/Ab"],"ibliograf":["http://dhi-roma.it/Ab"],"ibliogra":["http://dhi-roma.it/Ab"],"ibliogr":["http://dhi-roma.it/Ab"],"ibliog":["http://dhi-roma.it/Ab"],"iblio":["http://dhi-roma.it/Ab"],"ibli":["http://dhi-roma.it/Ab"],"ibl":["http://dhi-roma.it/Ab"],"ib":["http://dhi-roma.it/Ab"],"bliografie":["http://dhi-roma.it/Ab"],"bliografi":["http://dhi-roma.it/Ab"],"bliograf":["http://dhi-roma.it/Ab"],"bliogra":["http://dhi-roma.it/Ab"],"bliogr":["http://dhi-roma.it/Ab"],"bliog":["http://dhi-roma.it/Ab"],"blio":["http://dhi-roma.it/Ab"],"bli":["http://dhi-roma.it/Ab"],"bl":["http://dhi-roma.it/Ab"],"liografie":["http://dhi-roma.it/Ab"],"liografi":["http://dhi-roma.it/Ab"],"liograf":["http://dhi-roma.it/Ab"],"liogra":["http://dhi-roma.it/Ab"],"liogr":["http://dhi-roma.it/Ab"],"liog":["http://dhi-roma.it/Ab"],"lio":["http://dhi-roma.it/Ab"],"li":["http://dhi-roma.it/Ab","http://dhi-roma.it/Ba"],"iografie":["http://dhi-roma.it/Ab"],"iografi":["http://dhi-roma.it/Ab"],"iograf":["http://dhi-roma.it/Ab"],"iogra":["http://dhi-roma.it/Ab"],"iogr":["http://dhi-roma.it/Ab"],"iog":["http://dhi-roma.it/Ab"],"io":["http://dhi-roma.it/Ab"],"ografie":["http://dhi-roma.it/Ab"],"ografi":["http://dhi-roma.it/Ab","http://dhi-roma.it/Bi"],"ograf":["http://dhi-roma.it/Ab","http://dhi-roma.it/Bi"],"ogra":["http://dhi-roma.it/Ab","http://dhi-roma.it/Bi"],"ogr":["http://dhi-roma.it/Ab","http://dhi-roma.it/Bi"],"og":["http://dhi-roma.it/Ab","http://dhi-roma.it/Bd","http://dhi-roma.it/Be","http://dhi-roma.it/Bi"],"grafie":["http://dhi-roma.it/Ab"],"grafi":["http://dhi-roma.it/Ab","http://dhi-roma.it/Bi"],"graf":["http://dhi-roma.it/Ab","http://dhi-roma.it/Bi"],"gra":["http://dhi-roma.it/Ab","http://dhi-roma.it/Bi"],"gr":["http://dhi-roma.it/Ab","http://dhi-roma.it/Bi"],"g":["http://dhi-roma.it/Ab","http://dhi-roma.it/Ba","http://dhi-roma.it/Bd","http://dhi-roma.it/Be","http://dhi-roma.it/Bi"],"rafie":["http://dhi-roma.it/Ab"],"rafi":["http://dhi-roma.it/Ab","http://dhi-roma.it/Bi"],"raf":["http://dhi-roma.it/Ab","http://dhi-roma.it/Bi"],"ra":["http://dhi-roma.it/Ab","http://dhi-roma.it/Bb","http://dhi-roma.it/Bf","http://dhi-roma.it/Bi"],"r":["http://dhi-roma.it/Ab","http://dhi-roma.it/Ae","http://dhi-roma.it/Bb","http://dhi-roma.it/Bd","http://dhi-roma.it/Bf","http://dhi-roma.it/Bi","http://dhi-roma.it/C","http://dhi-roma.it/Ca","http://dhi-roma.it/Cb","http://dhi-roma.it/Cc"],"afie":["http://dhi-roma.it/Ab"],"afi":["http://dhi-roma.it/Ab","http://dhi-roma.it/Bi"],"af":["http://dhi-roma.it/Ab","http://dhi-roma.it/Bi"],"a":["http://dhi-roma.it/Ab","http://dhi-roma.it/Ac","http://dhi-roma.it/Ba","http://dhi-roma.it/Bb","http://dhi-roma.it/Bc","http://dhi-roma.it/Bd","http://dhi-roma.it/Be","http://dhi-roma.it/Bf","http://dhi-roma.it/Bg","http://dhi-roma.it/Bi","http://dhi-roma.it/C","http://dhi-roma.it/Ca","http://dhi-roma.it/Cb","http://dhi-roma.it/Cc"],"fie":["http://dhi-roma.it/Ab"],"fi":["http://dhi-roma.it/Ab","http://dhi-roma.it/Bi"],"f":["http://dhi-roma.it/Ab","http://dhi-roma.it/Ae","http://dhi-roma.it/Bi"],"miscellanea":["http://dhi-roma.it/Ac"],"miscellane":["http://dhi-roma.it/Ac"],"miscellan":["http://dhi-roma.it/Ac"],"miscella":["http://dhi-roma.it/Ac"],"miscell":["http://dhi-roma.it/Ac"],"miscel":["http://dhi-roma.it/Ac"],"misce":["http://dhi-roma.it/Ac"],"misc":["http://dhi-roma.it/Ac"],"mis":["http://dhi-roma.it/Ac","http://dhi-roma.it/Bg"],"mi":["http://dhi-roma.it/Ac","http://dhi-roma.it/Bg"],"m":["http://dhi-roma.it/Ac","http://dhi-roma.it/Bc","http://dhi-roma.it/Bg","http://dhi-roma.it/Bk"],"iscellanea":["http://dhi-roma.it/Ac"],"iscellane":["http://dhi-roma.it/Ac"],"iscellan":["http://dhi-roma.it/Ac"],"iscella":["http://dhi-roma.it/Ac"],"iscell":["http://dhi-roma.it/Ac"],"iscel":["http://dhi-roma.it/Ac"],"isce":["http://dhi-roma.it/Ac"],"isc":["http://dhi-roma.it/Ac"],"is":["http://dhi-roma.it/Ac","http://dhi-roma.it/Ba","http://dhi-roma.it/Bg"],"scellanea":["http://dhi-roma.it/Ac"],"scellane":["http://dhi-roma.it/Ac"],"scellan":["http://dhi-roma.it/Ac"],"scella":["http://dhi-roma.it/Ac"],"scell":["http://dhi-roma.it/Ac"],"scel":["http://dhi-roma.it/Ac"],"sce":["http://dhi-roma.it/Ac"],"sc":["http://dhi-roma.it/Ac","http://dhi-roma.it/Ae","http://dhi-roma.it/B","http://dhi-roma.it/Bb"],"s":["http://dhi-roma.it/Ac","http://dhi-roma.it/Ae","http://dhi-roma.it/B","http://dhi-roma.it/Ba","http://dhi-roma.it/Bb","http://dhi-roma.it/Bg"],"cellanea":["http://dhi-roma.it/Ac"],"cellane":["http://dhi-roma.it/Ac"],"cellan":["http://dhi-roma.it/Ac"],"cella":["http://dhi-roma.it/Ac"],"cell":["http://dhi-roma.it/Ac"],"cel":["http://dhi-roma.it/Ac"],"ce":["http://dhi-roma.it/Ac"],"ellanea":["http://dhi-roma.it/Ac"],"ellane":["http://dhi-roma.it/Ac"],"ellan":["http://dhi-roma.it/Ac"],"ella":["http://dhi-roma.it/Ac"],"ell":["http://dhi-roma.it/Ac"],"el":["http://dhi-roma.it/Ac"],"llanea":["http://dhi-roma.it/Ac"],"llane":["http://dhi-roma.it/Ac"],"llan":["http://dhi-roma.it/Ac"],"lla":["http://dhi-roma.it/Ac"],"ll":["http://dhi-roma.it/Ac"],"lanea":["http://dhi-roma.it/Ac"],"lane":["http://dhi-roma.it/Ac"],"lan":["http://dhi-roma.it/Ac"],"la":["http://dhi-roma.it/Ac"],"anea":["http://dhi-roma.it/Ac"],"ane":["http://dhi-roma.it/Ac"],"an":["http://dhi-roma.it/Ac"],"nea":["http://dhi-roma.it/Ac","http://dhi-roma.it/Be"],"ne":["http://dhi-roma.it/Ac","http://dhi-roma.it/Be"],"ea":["http://dhi-roma.it/Ac","http://dhi-roma.it/Be"],"festschriften":["http://dhi-roma.it/Ae"],"festschrifte":["http://dhi-roma.it/Ae"],"festschrift":["http://dhi-roma.it/Ae"],"festschrif":["http://dhi-roma.it/Ae"],"festschri":["http://dhi-roma.it/Ae"],"festschr":["http://dhi-roma.it/Ae"],"festsch":["http://dhi-roma.it/Ae"],"festsc":["http://dhi-roma.it/Ae"],"fests":["http://dhi-roma.it/Ae"],"fest":["http://dhi-roma.it/Ae"],"fes":["http://dhi-roma.it/Ae"],"fe":["http://dhi-roma.it/Ae"],"estschriften":["http://dhi-roma.it/Ae"],"estschrifte":["http://dhi-roma.it/Ae"],"estschrift":["http://dhi-roma.it/Ae"],"estschrif":["http://dhi-roma.it/Ae"],"estschri":["http://dhi-roma.it/Ae"],"estschr":["http://dhi-roma.it/Ae"],"estsch":["http://dhi-roma.it/Ae"],"estsc":["http://dhi-roma.it/Ae"],"ests":["http://dhi-roma.it/Ae"],"est":["http://dhi-roma.it/Ae"],"es":["http://dhi-roma.it/Ae"],"stschriften":["http://dhi-roma.it/Ae"],"stschrifte":["http://dhi-roma.it/Ae"],"stschrift":["http://dhi-roma.it/Ae"],"stschrif":["http://dhi-roma.it/Ae"],"stschri":["http://dhi-roma.it/Ae"],"stschr":["http://dhi-roma.it/Ae"],"stsch":["http://dhi-roma.it/Ae"],"stsc":["http://dhi-roma.it/Ae"],"sts":["http://dhi-roma.it/Ae"],"st":["http://dhi-roma.it/Ae","http://dhi-roma.it/Ba"],"tschriften":["http://dhi-roma.it/Ae"],"tschrifte":["http://dhi-roma.it/Ae"],"tschrift":["http://dhi-roma.it/Ae"],"tschrif":["http://dhi-roma.it/Ae"],"tschri":["http://dhi-roma.it/Ae"],"tschr":["http://dhi-roma.it/Ae"],"tsch":["http://dhi-roma.it/Ae"],"tsc":["http://dhi-roma.it/Ae"],"ts":["http://dhi-roma.it/Ae"],"t":["http://dhi-roma.it/Ae","http://dhi-roma.it/Ba","http://dhi-roma.it/Bb","http://dhi-roma.it/Bc","http://dhi-roma.it/Bg","http://dhi-roma.it/Bk"],"schriften":["http://dhi-roma.it/Ae"],"schrifte":["http://dhi-roma.it/Ae"],"schrift":["http://dhi-roma.it/Ae"],"schrif":["http://dhi-roma.it/Ae"],"schri":["http://dhi-roma.it/Ae"],"schr":["http://dhi-roma.it/Ae"],"sch":["http://dhi-roma.it/Ae"],"chriften":["http://dhi-roma.it/Ae"],"chrifte":["http://dhi-roma.it/Ae"],"chrift":["http://dhi-roma.it/Ae"],"chrif":["http://dhi-roma.it/Ae"],"chri":["http://dhi-roma.it/Ae"],"chr":["http://dhi-roma.it/Ae"],"ch":["http://dhi-roma.it/Ae","http://dhi-roma.it/C","http://dhi-roma.it/Ca","http://dhi-roma.it/Cb","http://dhi-roma.it/Cc"],"hriften":["http://dhi-roma.it/Ae"],"hrifte":["http://dhi-roma.it/Ae"],"hrift":["http://dhi-roma.it/Ae"],"hrif":["http://dhi-roma.it/Ae"],"hri":["http://dhi-roma.it/Ae"],"hr":["http://dhi-roma.it/Ae"],"h":["http://dhi-roma.it/Ae","http://dhi-roma.it/C","http://dhi-roma.it/Ca","http://dhi-roma.it/Cb","http://dhi-roma.it/Cc"],"riften":["http://dhi-roma.it/Ae"],"rifte":["http://dhi-roma.it/Ae"],"rift":["http://dhi-roma.it/Ae"],"rif":["http://dhi-roma.it/Ae"],"ri":["http://dhi-roma.it/Ae","http://dhi-roma.it/Bb"],"iften":["http://dhi-roma.it/Ae"],"ifte":["http://dhi-roma.it/Ae"],"ift":["http://dhi-roma.it/Ae"],"if":["http://dhi-roma.it/Ae"],"ften":["http://dhi-roma.it/Ae"],"fte":["http://dhi-roma.it/Ae"],"ft":["http://dhi-roma.it/Ae"],"ten":["http://dhi-roma.it/Ae"],"te":["http://dhi-roma.it/Ae"],"scienze":["http://dhi-roma.it/B"],"scienz":["http://dhi-roma.it/B"],"scien":["http://dhi-roma.it/B"],"scie":["http://dhi-roma.it/B"],"sci":["http://dhi-roma.it/B"],"cienze":["http://dhi-roma.it/B"],"cienz":["http://dhi-roma.it/B"],"cien":["http://dhi-roma.it/B"],"cie":["http://dhi-roma.it/B"],"ienze":["http://dhi-roma.it/B"],"ienz":["http://dhi-roma.it/B"],"ien":["http://dhi-roma.it/B"],"enze":["http://dhi-roma.it/B"],"enz":["http://dhi-roma.it/B"],"nze":["http://dhi-roma.it/B"],"nz":["http://dhi-roma.it/B"],"ze":["http://dhi-roma.it/B"],"z":["http://dhi-roma.it/B"],"linguistica":["http://dhi-roma.it/Ba"],"linguistic":["http://dhi-roma.it/Ba"],"linguisti":["http://dhi-roma.it/Ba"],"linguist":["http://dhi-roma.it/Ba"],"linguis":["http://dhi-roma.it/Ba"],"lingui":["http://dhi-roma.it/Ba"],"lingu":["http://dhi-roma.it/Ba"],"ling":["http://dhi-roma.it/Ba"],"lin":["http://dhi-roma.it/Ba"],"inguistica":["http://dhi-roma.it/Ba"],"inguistic":["http://dhi-roma.it/Ba"],"inguisti":["http://dhi-roma.it/Ba"],"inguist":["http://dhi-roma.it/Ba"],"inguis":["http://dhi-roma.it/Ba"],"ingui":["http://dhi-roma.it/Ba"],"ingu":["http://dhi-roma.it/Ba"],"ing":["http://dhi-roma.it/Ba"],"nguistica":["http://dhi-roma.it/Ba"],"nguistic":["http://dhi-roma.it/Ba"],"nguisti":["http://dhi-roma.it/Ba"],"nguist":["http://dhi-roma.it/Ba"],"nguis":["http://dhi-roma.it/Ba"],"ngui":["http://dhi-roma.it/Ba"],"ngu":["http://dhi-roma.it/Ba"],"ng":["http://dhi-roma.it/Ba"],"guistica":["http://dhi-roma.it/Ba"],"guistic":["http://dhi-roma.it/Ba"],"guisti":["http://dhi-roma.it/Ba"],"guist":["http://dhi-roma.it/Ba"],"guis":["http://dhi-roma.it/Ba"],"gui":["http://dhi-roma.it/Ba"],"gu":["http://dhi-roma.it/Ba"],"uistica":["http://dhi-roma.it/Ba"],"uistic":["http://dhi-roma.it/Ba"],"uisti":["http://dhi-roma.it/Ba"],"uist":["http://dhi-roma.it/Ba"],"uis":["http://dhi-roma.it/Ba"],"ui":["http://dhi-roma.it/Ba"],"u":["http://dhi-roma.it/Ba","http://dhi-roma.it/Bb","http://dhi-roma.it/Bg"],"istica":["http://dhi-roma.it/Ba"],"istic":["http://dhi-roma.it/Ba"],"isti":["http://dhi-roma.it/Ba"],"ist":["http://dhi-roma.it/Ba"],"stica":["http://dhi-roma.it/Ba"],"stic":["http://dhi-roma.it/Ba"],"sti":["http://dhi-roma.it/Ba"],"tica":["http://dhi-roma.it/Ba","http://dhi-roma.it/Bc","http://dhi-roma.it/Bg"],"tic":["http://dhi-roma.it/Ba","http://dhi-roma.it/Bc","http://dhi-roma.it/Bg"],"ti":["http://dhi-roma.it/Ba","http://dhi-roma.it/Bc","http://dhi-roma.it/Bg"],"ica":["http://dhi-roma.it/Ba","http://dhi-roma.it/Bc","http://dhi-roma.it/Bf","http://dhi-roma.it/Bg"],"ca":["http://dhi-roma.it/Ba","http://dhi-roma.it/Bc","http://dhi-roma.it/Bf","http://dhi-roma.it/Bg"],"scrittura":["http://dhi-roma.it/Bb"],"scrittur":["http://dhi-roma.it/Bb"],"scrittu":["http://dhi-roma.it/Bb"],"scritt":["http://dhi-roma.it/Bb"],"scrit":["http://dhi-roma.it/Bb"],"scri":["http://dhi-roma.it/Bb"],"scr":["http://dhi-roma.it/Bb"],"crittura":["http://dhi-roma.it/Bb"],"crittur":["http://dhi-roma.it/Bb"],"crittu":["http://dhi-roma.it/Bb"],"critt":["http://dhi-roma.it/Bb"],"crit":["http://dhi-roma.it/Bb"],"cri":["http://dhi-roma.it/Bb"],"cr":["http://dhi-roma.it/Bb","http://dhi-roma.it/Bd"],"rittura":["http://dhi-roma.it/Bb"],"rittur":["http://dhi-roma.it/Bb"],"rittu":["http://dhi-roma.it/Bb"],"ritt":["http://dhi-roma.it/Bb"],"rit":["http://dhi-roma.it/Bb"],"ittura":["http://dhi-roma.it/Bb"],"ittur":["http://dhi-roma.it/Bb"],"ittu":["http://dhi-roma.it/Bb"],"itt":["http://dhi-roma.it/Bb"],"it":["http://dhi-roma.it/Bb"],"ttura":["http://dhi-roma.it/Bb"],"ttur":["http://dhi-roma.it/Bb"],"ttu":["http://dhi-roma.it/Bb"],"tt":["http://dhi-roma.it/Bb"],"tura":["http://dhi-roma.it/Bb"],"tur":["http://dhi-roma.it/Bb"],"tu":["http://dhi-roma.it/Bb"],"ura":["http://dhi-roma.it/Bb"],"ur":["http://dhi-roma.it/Bb"],"diplomatica":["http://dhi-roma.it/Bc"],"diplomatic":["http://dhi-roma.it/Bc"],"diplomati":["http://dhi-roma.it/Bc"],"diplomat":["http://dhi-roma.it/Bc"],"diploma":["http://dhi-roma.it/Bc"],"diplom":["http://dhi-roma.it/Bc"],"diplo":["http://dhi-roma.it/Bc"],"dipl":["http://dhi-roma.it/Bc"],"dip":["http://dhi-roma.it/Bc"],"iplomatica":["http://dhi-roma.it/Bc"],"iplomatic":["http://dhi-roma.it/Bc"],"iplomati":["http://dhi-roma.it/Bc"],"iplomat":["http://dhi-roma.it/Bc"],"iploma":["http://dhi-roma.it/Bc"],"iplom":["http://dhi-roma.it/Bc"],"iplo":["http://dhi-roma.it/Bc"],"ipl":["http://dhi-roma.it/Bc"],"ip":["http://dhi-roma.it/Bc"],"plomatica":["http://dhi-roma.it/Bc"],"plomatic":["http://dhi-roma.it/Bc"],"plomati":["http://dhi-roma.it/Bc"],"plomat":["http://dhi-roma.it/Bc"],"ploma":["http://dhi-roma.it/Bc"],"plom":["http://dhi-roma.it/Bc"],"plo":["http://dhi-roma.it/Bc"],"pl":["http://dhi-roma.it/Bc"],"lomatica":["http://dhi-roma.it/Bc"],"lomatic":["http://dhi-roma.it/Bc"],"lomati":["http://dhi-roma.it/Bc"],"lomat":["http://dhi-roma.it/Bc"],"loma":["http://dhi-roma.it/Bc"],"lom":["http://dhi-roma.it/Bc"],"omatica":["http://dhi-roma.it/Bc"],"omatic":["http://dhi-roma.it/Bc"],"omati":["http://dhi-roma.it/Bc"],"omat":["http://dhi-roma.it/Bc"],"oma":["http://dhi-roma.it/Bc"],"om":["http://dhi-roma.it/Bc"],"matica":["http://dhi-roma.it/Bc","http://dhi-roma.it/Bg"],"matic":["http://dhi-roma.it/Bc","http://dhi-roma.it/Bg"],"mati":["http://dhi-roma.it/Bc","http://dhi-roma.it/Bg"],"mat":["http://dhi-roma.it/Bc","http://dhi-roma.it/Bg"],"ma":["http://dhi-roma.it/Bc","http://dhi-roma.it/Bg"],"atica":["http://dhi-roma.it/Bc","http://dhi-roma.it/Bg"],"atic":["http://dhi-roma.it/Bc","http://dhi-roma.it/Bg"],"ati":["http://dhi-roma.it/Bc","http://dhi-roma.it/Bg"],"at":["http://dhi-roma.it/Bc","http://dhi-roma.it/Bg"],"cronologia":["http://dhi-roma.it/Bd"],"cronologi":["http://dhi-roma.it/Bd"],"cronolog":["http://dhi-roma.it/Bd"],"cronolo":["http://dhi-roma.it/Bd"],"cronol":["http://dhi-roma.it/Bd"],"crono":["http://dhi-roma.it/Bd"],"cron":["http://dhi-roma.it/Bd"],"cro":["http://dhi-roma.it/Bd"],"ronologia":["http://dhi-roma.it/Bd"],"ronologi":["http://dhi-roma.it/Bd"],"ronolog":["http://dhi-roma.it/Bd"],"ronolo":["http://dhi-roma.it/Bd"],"ronol":["http://dhi-roma.it/Bd"],"rono":["http://dhi-roma.it/Bd"],"ron":["http://dhi-roma.it/Bd"],"ro":["http://dhi-roma.it/Bd"],"onologia":["http://dhi-roma.it/Bd"],"onologi":["http://dhi-roma.it/Bd"],"onolog":["http://dhi-roma.it/Bd"],"onolo":["http://dhi-roma.it/Bd"],"onol":["http://dhi-roma.it/Bd"],"ono":["http://dhi-roma.it/Bd"],"on":["http://dhi-roma.it/Bd"],"nologia":["http://dhi-roma.it/Bd"],"nologi":["http://dhi-roma.it/Bd"],"nolog":["http://dhi-roma.it/Bd"],"nolo":["http://dhi-roma.it/Bd"],"nol":["http://dhi-roma.it/Bd"],"no":["http://dhi-roma.it/Bd"],"ologia":["http://dhi-roma.it/Bd"],"ologi":["http://dhi-roma.it/Bd"],"olog":["http://dhi-roma.it/Bd"],"olo":["http://dhi-roma.it/Bd"],"ol":["http://dhi-roma.it/Bd"],"logia":["http://dhi-roma.it/Bd","http://dhi-roma.it/Be"],"logi":["http://dhi-roma.it/Bd","http://dhi-roma.it/Be"],"log":["http://dhi-roma.it/Bd","http://dhi-roma.it/Be"],"ogia":["http://dhi-roma.it/Bd","http://dhi-roma.it/Be"],"ogi":["http://dhi-roma.it/Bd","http://dhi-roma.it/Be"],"gia":["http://dhi-roma.it/Bd","http://dhi-roma.it/Be"],"gi":["http://dhi-roma.it/Bd","http://dhi-roma.it/Be"],"ia":["http://dhi-roma.it/Bd","http://dhi-roma.it/Be","http://dhi-roma.it/Bi"],"genealogia":["http://dhi-roma.it/Be"],"genealogi":["http://dhi-roma.it/Be"],"genealog":["http://dhi-roma.it/Be"],"genealo":["http://dhi-roma.it/Be"],"geneal":["http://dhi-roma.it/Be"],"genea":["http://dhi-roma.it/Be"],"gene":["http://dhi-roma.it/Be"],"gen":["http://dhi-roma.it/Be"],"ge":["http://dhi-roma.it/Be","http://dhi-roma.it/Bi"],"enealogia":["http://dhi-roma.it/Be"],"enealogi":["http://dhi-roma.it/Be"],"enealog":["http://dhi-roma.it/Be"],"enealo":["http://dhi-roma.it/Be"],"eneal":["http://dhi-roma.it/Be"],"enea":["http://dhi-roma.it/Be"],"ene":["http://dhi-roma.it/Be"],"nealogia":["http://dhi-roma.it/Be"],"nealogi":["http://dhi-roma.it/Be"],"nealog":["http://dhi-roma.it/Be"],"nealo":["http://dhi-roma.it/Be"],"neal":["http://dhi-roma.it/Be"],"ealogia":["http://dhi-roma.it/Be"],"ealogi":["http://dhi-roma.it/Be"],"ealog":["http://dhi-roma.it/Be"],"ealo":["http://dhi-roma.it/Be"],"eal":["http://dhi-roma.it/Be"],"alogia":["http://dhi-roma.it/Be"],"alogi":["http://dhi-roma.it/Be"],"alog":["http://dhi-roma.it/Be"],"alo":["http://dhi-roma.it/Be"],"al":["http://dhi-roma.it/Be","http://dhi-roma.it/Bf"],"araldica":["http://dhi-roma.it/Bf"],"araldic":["http://dhi-roma.it/Bf"],"araldi":["http://dhi-roma.it/Bf"],"arald":["http://dhi-roma.it/Bf"],"aral":["http://dhi-roma.it/Bf"],"ara":["http://dhi-roma.it/Bf"],"ar":["http://dhi-roma.it/Bf","http://dhi-roma.it/C","http://dhi-roma.it/Ca","http://dhi-roma.it/Cb","http://dhi-roma.it/Cc"],"raldica":["http://dhi-roma.it/Bf"],"raldic":["http://dhi-roma.it/Bf"],"raldi":["http://dhi-roma.it/Bf"],"rald":["http://dhi-roma.it/Bf"],"ral":["http://dhi-roma.it/Bf"],"aldica":["http://dhi-roma.it/Bf"],"aldic":["http://dhi-roma.it/Bf"],"aldi":["http://dhi-roma.it/Bf"],"ald":["http://dhi-roma.it/Bf"],"ldica":["http://dhi-roma.it/Bf"],"ldic":["http://dhi-roma.it/Bf"],"ldi":["http://dhi-roma.it/Bf"],"ld":["http://dhi-roma.it/Bf"],"dica":["http://dhi-roma.it/Bf"],"dic":["http://dhi-roma.it/Bf"],"numismatica":["http://dhi-roma.it/Bg"],"numismatic":["http://dhi-roma.it/Bg"],"numismati":["http://dhi-roma.it/Bg"],"numismat":["http://dhi-roma.it/Bg"],"numisma":["http://dhi-roma.it/Bg"],"numism":["http://dhi-roma.it/Bg"],"numis":["http://dhi-roma.it/Bg"],"numi":["http://dhi-roma.it/Bg"],"num":["http://dhi-roma.it/Bg"],"nu":["http://dhi-roma.it/Bg"],"umismatica":["http://dhi-roma.it/Bg"],"umismatic":["http://dhi-roma.it/Bg"],"umismati":["http://dhi-roma.it/Bg"],"umismat":["http://dhi-roma.it/Bg"],"umisma":["http://dhi-roma.it/Bg"],"umism":["http://dhi-roma.it/Bg"],"umis":["http://dhi-roma.it/Bg"],"umi":["http://dhi-roma.it/Bg"],"um":["http://dhi-roma.it/Bg"],"mismatica":["http://dhi-roma.it/Bg"],"mismatic":["http://dhi-roma.it/Bg"],"mismati":["http://dhi-roma.it/Bg"],"mismat":["http://dhi-roma.it/Bg"],"misma":["http://dhi-roma.it/Bg"],"mism":["http://dhi-roma.it/Bg"],"ismatica":["http://dhi-roma.it/Bg"],"ismatic":["http://dhi-roma.it/Bg"],"ismati":["http://dhi-roma.it/Bg"],"ismat":["http://dhi-roma.it/Bg"],"isma":["http://dhi-roma.it/Bg"],"ism":["http://dhi-roma.it/Bg"],"smatica":["http://dhi-roma.it/Bg"],"smatic":["http://dhi-roma.it/Bg"],"smati":["http://dhi-roma.it/Bg"],"smat":["http://dhi-roma.it/Bg"],"sma":["http://dhi-roma.it/Bg"],"sm":["http://dhi-roma.it/Bg"],"geografia":["http://dhi-roma.it/Bi"],"geografi":["http://dhi-roma.it/Bi"],"geograf":["http://dhi-roma.it/Bi"],"geogra":["http://dhi-roma.it/Bi"],"geogr":["http://dhi-roma.it/Bi"],"geog":["http://dhi-roma.it/Bi"],"geo":["http://dhi-roma.it/Bi"],"eografia":["http://dhi-roma.it/Bi"],"eografi":["http://dhi-roma.it/Bi"],"eograf":["http://dhi-roma.it/Bi"],"eogra":["http://dhi-roma.it/Bi"],"eogr":["http://dhi-roma.it/Bi"],"eog":["http://dhi-roma.it/Bi"],"eo":["http://dhi-roma.it/Bi"],"ografia":["http://dhi-roma.it/Bi"],"grafia":["http://dhi-roma.it/Bi"],"rafia":["http://dhi-roma.it/Bi"],"afia":["http://dhi-roma.it/Bi"],"fia":["http://dhi-roma.it/Bi"],"metodo":["http://dhi-roma.it/Bk"],"metod":["http://dhi-roma.it/Bk"],"meto":["http://dhi-roma.it/Bk"],"met":["http://dhi-roma.it/Bk"],"me":["http://dhi-roma.it/Bk"],"etodo":["http://dhi-roma.it/Bk"],"etod":["http://dhi-roma.it/Bk"],"eto":["http://dhi-roma.it/Bk"],"et":["http://dhi-roma.it/Bk"],"todo":["http://dhi-roma.it/Bk"],"tod":["http://dhi-roma.it/Bk"],"to":["http://dhi-roma.it/Bk"],"odo":["http://dhi-roma.it/Bk"],"od":["http://dhi-roma.it/Bk"],"do":["http://dhi-roma.it/Bk"],"archivi":["http://dhi-roma.it/C","http://dhi-roma.it/Ca","http://dhi-roma.it/Cc"],"archiv":["http://dhi-roma.it/C","http://dhi-roma.it/Ca","http://dhi-roma.it/Cb","http://dhi-roma.it/Cc"],"archi":["http://dhi-roma.it/C","http://dhi-roma.it/Ca","http://dhi-roma.it/Cb","http://dhi-roma.it/Cc"],"arch":["http://dhi-roma.it/C","http://dhi-roma.it/Ca","http://dhi-roma.it/Cb","http://dhi-roma.it/Cc"],"arc":["http://dhi-roma.it/C","http://dhi-roma.it/Ca","http://dhi-roma.it/Cb","http://dhi-roma.it/Cc"],"rchivi":["http://dhi-roma.it/C","http://dhi-roma.it/Ca","http://dhi-roma.it/Cc"],"rchiv":["http://dhi-roma.it/C","http://dhi-roma.it/Ca","http://dhi-roma.it/Cb","http://dhi-roma.it/Cc"],"rchi":["http://dhi-roma.it/C","http://dhi-roma.it/Ca","http://dhi-roma.it/Cb","http://dhi-roma.it/Cc"],"rch":["http://dhi-roma.it/C","http://dhi-roma.it/Ca","http://dhi-roma.it/Cb","http://dhi-roma.it/Cc"],"rc":["http://dhi-roma.it/C","http://dhi-roma.it/Ca","http://dhi-roma.it/Cb","http://dhi-roma.it/Cc"],"chivi":["http://dhi-roma.it/C","http://dhi-roma.it/Ca","http://dhi-roma.it/Cc"],"chiv":["http://dhi-roma.it/C","http://dhi-roma.it/Ca","http://dhi-roma.it/Cb","http://dhi-roma.it/Cc"],"chi":["http://dhi-roma.it/C","http://dhi-roma.it/Ca","http://dhi-roma.it/Cb","http://dhi-roma.it/Cc"],"hivi":["http://dhi-roma.it/C","http://dhi-roma.it/Ca","http://dhi-roma.it/Cc"],"hiv":["http://dhi-roma.it/C","http://dhi-roma.it/Ca","http://dhi-roma.it/Cb","http://dhi-roma.it/Cc"],"hi":["http://dhi-roma.it/C","http://dhi-roma.it/Ca","http://dhi-roma.it/Cb","http://dhi-roma.it/Cc"],"ivi":["http://dhi-roma.it/C","http://dhi-roma.it/Ca","http://dhi-roma.it/Cc"],"iv":["http://dhi-roma.it/C","http://dhi-roma.it/Ca","http://dhi-roma.it/Cb","http://dhi-roma.it/Cc"],"vi":["http://dhi-roma.it/C","http://dhi-roma.it/Ca","http://dhi-roma.it/Cc"],"v":["http://dhi-roma.it/C","http://dhi-roma.it/Ca","http://dhi-roma.it/Cb","http://dhi-roma.it/Cc"],"archivl":["http://dhi-roma.it/Cb"],"rchivl":["http://dhi-roma.it/Cb"],"chivl":["http://dhi-roma.it/Cb"],"hivl":["http://dhi-roma.it/Cb"],"ivl":["http://dhi-roma.it/Cb"],"vl":["http://dhi-roma.it/Cb"]},{"generale":["http://dhi-roma.it/A"],"general":["http://dhi-roma.it/A"],"genera":["http://dhi-roma.it/A"],"gener":["http://dhi-roma.it/A"],"gene":["http://dhi-roma.it/A"],"gen":["http://dhi-roma.it/A"],"ge":["http://dhi-roma.it/A"],"g":["http://dhi-roma.it/A"],"lessici":["http://dhi-roma.it/Aa"],"lessic":["http://dhi-roma.it/Aa"],"lessi":["http://dhi-roma.it/Aa"],"less":["http://dhi-roma.it/Aa"],"les":["http://dhi-roma.it/Aa"],"le":["http://dhi-roma.it/Aa"],"serie":["http://dhi-roma.it/Ac"],"seri":["http://dhi-roma.it/Ac"],"ser":["http://dhi-roma.it/Ac"],"se":["http://dhi-roma.it/Ac"],"scritti":["http://dhi-roma.it/Ae"],"scritt":["http://dhi-roma.it/Ae"],"scrit":["http://dhi-roma.it/Ae"],"scri":["http://dhi-roma.it/Ae"],"scr":["http://dhi-roma.it/Ae"],"storiche":["http://dhi-roma.it/B"],"storich":["http://dhi-roma.it/B"],"storic":["http://dhi-roma.it/B"],"stori":["http://dhi-roma.it/B"],"stor":["http://dhi-roma.it/B"],"sto":["http://dhi-roma.it/B"],"st":["http://dhi-roma.it/B"],"e":["http://dhi-roma.it/Bf","http://dhi-roma.it/Ca","http://dhi-roma.it/Cb","http://dhi-roma.it/Cc"],"biblioteche":["http://dhi-roma.it/C","http://dhi-roma.it/Cc"],"bibliotech":["http://dhi-roma.it/C","http://dhi-roma.it/Cc"],"bibliotec":["http://dhi-roma.it/C","http://dhi-roma.it/Cc"],"bibliote":["http://dhi-roma.it/C","http://dhi-roma.it/Cc"],"bibliot":["http://dhi-roma.it/C","http://dhi-roma.it/Cc"],"biblio":["http://dhi-roma.it/C","http://dhi-roma.it/Cc"],"bibli":["http://dhi-roma.it/C","http://dhi-roma.it/Cc"],"bibl":["http://dhi-roma.it/C","http://dhi-roma.it/Cc"],"bib":["http://dhi-roma.it/C","http://dhi-roma.it/Cc"],"bi":["http://dhi-roma.it/C","http://dhi-roma.it/Cc"],"b":["http://dhi-roma.it/C","http://dhi-roma.it/Cc"]},{"enerale":["http://dhi-roma.it/A"],"eneral":["http://dhi-roma.it/A"],"enera":["http://dhi-roma.it/A"],"ener":["http://dhi-roma.it/A","http://dhi-roma.it/Aa"],"ene":["http://dhi-roma.it/A","http://dhi-roma.it/Aa"],"en":["http://dhi-roma.it/A"],"e":["http://dhi-roma.it/A"],"essici":["http://dhi-roma.it/Aa"],"essic":["http://dhi-roma.it/Aa"],"essi":["http://dhi-roma.it/Aa"],"ess":["http://dhi-roma.it/Aa"],"es":["http://dhi-roma.it/Aa"],"generäli":["http://dhi-roma.it/Aa"],"generäl":["http://dhi-roma.it/Aa"],"generä":["http://dhi-roma.it/Aa"],"gener":["http://dhi-roma.it/Aa"],"gene":["http://dhi-roma.it/Aa"],"gen":["http://dhi-roma.it/Aa"],"ge":["http://dhi-roma.it/Aa"],"g":["http://dhi-roma.it/Aa"],"eneräli":["http://dhi-roma.it/Aa"],"eneräl":["http://dhi-roma.it/Aa"],"enerä":["http://dhi-roma.it/Aa"],"erie":["http://dhi-roma.it/Ac"],"eri":["http://dhi-roma.it/Ac"],"er":["http://dhi-roma.it/Ac"],"ecc":["http://dhi-roma.it/Ac"],"ec":["http://dhi-roma.it/Ac"],"critti":["http://dhi-roma.it/Ae"],"critt":["http://dhi-roma.it/Ae"],"crit":["http://dhi-roma.it/Ae"],"cri":["http://dhi-roma.it/Ae"],"cr":["http://dhi-roma.it/Ae"],"ritti":["http://dhi-roma.it/Ae"],"ritt":["http://dhi-roma.it/Ae"],"rit":["http://dhi-roma.it/Ae"],"in":["http://dhi-roma.it/Ae"],"toriche":["http://dhi-roma.it/B"],"torich":["http://dhi-roma.it/B"],"toric":["http://dhi-roma.it/B"],"tori":["http://dhi-roma.it/B","http://dhi-roma.it/Bk"],"tor":["http://dhi-roma.it/B","http://dhi-roma.it/Bk"],"to":["http://dhi-roma.it/B"],"t":["http://dhi-roma.it/B"],"ausiliarie":["http://dhi-roma.it/B"],"ausiliari":["http://dhi-roma.it/B"],"ausiliar":["http://dhi-roma.it/B"],"ausilia":["http://dhi-roma.it/B"],"ausili":["http://dhi-roma.it/B"],"ausil":["http://dhi-roma.it/B"],"ausi":["http://dhi-roma.it/B"],"aus":["http://dhi-roma.it/B"],"au":["http://dhi-roma.it/B"],"a":["http://dhi-roma.it/B"],"usiliarie":["http://dhi-roma.it/B"],"usiliari":["http://dhi-roma.it/B"],"usiliar":["http://dhi-roma.it/B"],"usilia":["http://dhi-roma.it/B"],"usili":["http://dhi-roma.it/B"],"usil":["http://dhi-roma.it/B"],"usi":["http://dhi-roma.it/B"],"us":["http://dhi-roma.it/B"],"u":["http://dhi-roma.it/B"],"sfragistica":["http://dhi-roma.it/Bf"],"sfragistic":["http://dhi-roma.it/Bf"],"sfragisti":["http://dhi-roma.it/Bf"],"sfragist":["http://dhi-roma.it/Bf"],"sfragis":["http://dhi-roma.it/Bf"],"sfragi":["http://dhi-roma.it/Bf"],"sfrag":["http://dhi-roma.it/Bf"],"sfra":["http://dhi-roma.it/Bf"],"sfr":["http://dhi-roma.it/Bf"],"sf":["http://dhi-roma.it/Bf"],"s":["http://dhi-roma.it/Bf","http://dhi-roma.it/Bk","http://dhi-roma.it/Cb"],"fragistica":["http://dhi-roma.it/Bf"],"fragistic":["http://dhi-roma.it/Bf"],"fragisti":["http://dhi-roma.it/Bf"],"fragist":["http://dhi-roma.it/Bf"],"fragis":["http://dhi-roma.it/Bf"],"fragi":["http://dhi-roma.it/Bf"],"frag":["http://dhi-roma.it/Bf"],"fra":["http://dhi-roma.it/Bf"],"fr":["http://dhi-roma.it/Bf"],"f":["http://dhi-roma.it/Bf"],"storia":["http://dhi-roma.it/Bk"],"stori":["http://dhi-roma.it/Bk"],"stor":["http://dhi-roma.it/Bk"],"sto":["http://dhi-roma.it/Bk"],"st":["http://dhi-roma.it/Bk"],"toria":["http://dhi-roma.it/Bk"],"storiografia":["http://dhi-roma.it/Bk"],"storiografi":["http://dhi-roma.it/Bk"],"storiograf":["http://dhi-roma.it/Bk"],"storiogra":["http://dhi-roma.it/Bk"],"storiogr":["http://dhi-roma.it/Bk"],"storiog":["http://dhi-roma.it/Bk"],"storio":["http://dhi-roma.it/Bk"],"iblioteche":["http://dhi-roma.it/C","http://dhi-roma.it/Ca","http://dhi-roma.it/Cb","http://dhi-roma.it/Cc"],"ibliotech":["http://dhi-roma.it/C","http://dhi-roma.it/Ca","http://dhi-roma.it/Cb","http://dhi-roma.it/Cc"],"ibliotec":["http://dhi-roma.it/C","http://dhi-roma.it/Ca","http://dhi-roma.it/Cb","http://dhi-roma.it/Cc"],"ibliote":["http://dhi-roma.it/C","http://dhi-roma.it/Ca","http://dhi-roma.it/Cb","http://dhi-roma.it/Cc"],"ibliot":["http://dhi-roma.it/C","http://dhi-roma.it/Ca","http://dhi-roma.it/Cb","http://dhi-roma.it/Cc"],"iblio":["http://dhi-roma.it/C","http://dhi-roma.it/Ca","http://dhi-roma.it/Cb","http://dhi-roma.it/Cc"],"ibli":["http://dhi-roma.it/C","http://dhi-roma.it/Ca","http://dhi-roma.it/Cb","http://dhi-roma.it/Cc"],"ibl":["http://dhi-roma.it/C","http://dhi-roma.it/Ca","http://dhi-roma.it/Cb","http://dhi-roma.it/Cc"],"ib":["http://dhi-roma.it/C","http://dhi-roma.it/Ca","http://dhi-roma.it/Cb","http://dhi-roma.it/Cc"],"blioteche":["http://dhi-roma.it/C","http://dhi-roma.it/Cc"],"bliotech":["http://dhi-roma.it/C","http://dhi-roma.it/Cc"],"bliotec":["http://dhi-roma.it/C","http://dhi-roma.it/Cc"],"bliote":["http://dhi-roma.it/C","http://dhi-roma.it/Cc"],"bliot":["http://dhi-roma.it/C","http://dhi-roma.it/Cc"],"blio":["http://dhi-roma.it/C","http://dhi-roma.it/Cc"],"bli":["http://dhi-roma.it/C","http://dhi-roma.it/Cc"],"bl":["http://dhi-roma.it/C","http://dhi-roma.it/Cc"],"istituti":["http://dhi-roma.it/C"],"istitut":["http://dhi-roma.it/C"],"istitu":["http://dhi-roma.it/C"],"istit":["http://dhi-roma.it/C"],"isti":["http://dhi-roma.it/C"],"ist":["http://dhi-roma.it/C"],"is":["http://dhi-roma.it/C"],"biblioteche":["http://dhi-roma.it/Ca","http://dhi-roma.it/Cb"],"bibliotech":["http://dhi-roma.it/Ca","http://dhi-roma.it/Cb"],"bibliotec":["http://dhi-roma.it/Ca","http://dhi-roma.it/Cb"],"bibliote":["http://dhi-roma.it/Ca","http://dhi-roma.it/Cb"],"bibliot":["http://dhi-roma.it/Ca","http://dhi-roma.it/Cb"],"biblio":["http://dhi-roma.it/Ca","http://dhi-roma.it/Cb"],"bibli":["http://dhi-roma.it/Ca","http://dhi-roma.it/Cb"],"bibl":["http://dhi-roma.it/Ca","http://dhi-roma.it/Cb"],"bib":["http://dhi-roma.it/Ca","http://dhi-roma.it/Cb"],"bi":["http://dhi-roma.it/Ca","http://dhi-roma.it/Cb"],"b":["http://dhi-roma.it/Ca","http://dhi-roma.it/Cb"],"specifiche":["http://dhi-roma.it/Cb"],"specifich":["http://dhi-roma.it/Cb"],"specific":["http://dhi-roma.it/Cb"],"specifi":["http://dhi-roma.it/Cb"],"specif":["http://dhi-roma.it/Cb"],"speci":["http://dhi-roma.it/Cb"],"spec":["http://dhi-roma.it/Cb"],"spe":["http://dhi-roma.it/Cb"],"sp":["http://dhi-roma.it/Cb"]},{"nerale":["http://dhi-roma.it/A"],"neral":["http://dhi-roma.it/A"],"nera":["http://dhi-roma.it/A"],"ner":["http://dhi-roma.it/A","http://dhi-roma.it/Aa"],"ne":["http://dhi-roma.it/A","http://dhi-roma.it/Aa"],"ssici":["http://dhi-roma.it/Aa"],"ssic":["http://dhi-roma.it/Aa"],"ssi":["http://dhi-roma.it/Aa"],"ss":["http://dhi-roma.it/Aa"],"s":["http://dhi-roma.it/Aa","http://dhi-roma.it/C"],"sici":["http://dhi-roma.it/Aa"],"sic":["http://dhi-roma.it/Aa"],"si":["http://dhi-roma.it/Aa","http://dhi-roma.it/B"],"neräli":["http://dhi-roma.it/Aa"],"neräl":["http://dhi-roma.it/Aa"],"nerä":["http://dhi-roma.it/Aa"],"biografici":["http://dhi-roma.it/Aa"],"biografic":["http://dhi-roma.it/Aa"],"biografi":["http://dhi-roma.it/Aa"],"biograf":["http://dhi-roma.it/Aa"],"biogra":["http://dhi-roma.it/Aa"],"biogr":["http://dhi-roma.it/Aa"],"biog":["http://dhi-roma.it/Aa"],"bio":["http://dhi-roma.it/Aa"],"bi":["http://dhi-roma.it/Aa"],"b":["http://dhi-roma.it/Aa"],"iografici":["http://dhi-roma.it/Aa"],"iografic":["http://dhi-roma.it/Aa"],"iografi":["http://dhi-roma.it/Aa"],"iograf":["http://dhi-roma.it/Aa"],"iogra":["http://dhi-roma.it/Aa"],"iogr":["http://dhi-roma.it/Aa"],"iog":["http://dhi-roma.it/Aa"],"io":["http://dhi-roma.it/Aa","http://dhi-roma.it/C","http://dhi-roma.it/Cc"],"rie":["http://dhi-roma.it/Ac"],"ri":["http://dhi-roma.it/Ac","http://dhi-roma.it/B"],"r":["http://dhi-roma.it/Ac","http://dhi-roma.it/B"],"cc":["http://dhi-roma.it/Ac"],"itti":["http://dhi-roma.it/Ae"],"itt":["http://dhi-roma.it/Ae"],"it":["http://dhi-roma.it/Ae","http://dhi-roma.it/Cc"],"onore":["http://dhi-roma.it/Ae"],"onor":["http://dhi-roma.it/Ae"],"ono":["http://dhi-roma.it/Ae"],"on":["http://dhi-roma.it/Ae"],"o":["http://dhi-roma.it/Ae","http://dhi-roma.it/B"],"nore":["http://dhi-roma.it/Ae"],"nor":["http://dhi-roma.it/Ae"],"no":["http://dhi-roma.it/Ae"],"oriche":["http://dhi-roma.it/B"],"orich":["http://dhi-roma.it/B"],"oric":["http://dhi-roma.it/B"],"ori":["http://dhi-roma.it/B","http://dhi-roma.it/Bk"],"or":["http://dhi-roma.it/B","http://dhi-roma.it/Bk"],"riche":["http://dhi-roma.it/B"],"rich":["http://dhi-roma.it/B"],"ric":["http://dhi-roma.it/B"],"siliarie":["http://dhi-roma.it/B"],"siliari":["http://dhi-roma.it/B"],"siliar":["http://dhi-roma.it/B"],"silia":["http://dhi-roma.it/B"],"sili":["http://dhi-roma.it/B"],"sil":["http://dhi-roma.it/B"],"ragistica":["http://dhi-roma.it/Bf"],"ragistic":["http://dhi-roma.it/Bf"],"ragisti":["http://dhi-roma.it/Bf"],"ragist":["http://dhi-roma.it/Bf"],"ragis":["http://dhi-roma.it/Bf"],"ragi":["http://dhi-roma.it/Bf"],"rag":["http://dhi-roma.it/Bf"],"agistica":["http://dhi-roma.it/Bf"],"agistic":["http://dhi-roma.it/Bf"],"agisti":["http://dhi-roma.it/Bf"],"agist":["http://dhi-roma.it/Bf"],"agis":["http://dhi-roma.it/Bf"],"agi":["http://dhi-roma.it/Bf"],"ag":["http://dhi-roma.it/Bf"],"oria":["http://dhi-roma.it/Bk"],"della":["http://dhi-roma.it/Bk"],"dell":["http://dhi-roma.it/Bk"],"del":["http://dhi-roma.it/Bk"],"de":["http://dhi-roma.it/Bk"],"ella":["http://dhi-roma.it/Bk"],"ell":["http://dhi-roma.it/Bk"],"el":["http://dhi-roma.it/Bk"],"toriografia":["http://dhi-roma.it/Bk"],"toriografi":["http://dhi-roma.it/Bk"],"toriograf":["http://dhi-roma.it/Bk"],"toriogra":["http://dhi-roma.it/Bk"],"toriogr":["http://dhi-roma.it/Bk"],"toriog":["http://dhi-roma.it/Bk"],"torio":["http://dhi-roma.it/Bk"],"oriografia":["http://dhi-roma.it/Bk"],"oriografi":["http://dhi-roma.it/Bk"],"oriograf":["http://dhi-roma.it/Bk"],"oriogra":["http://dhi-roma.it/Bk"],"oriogr":["http://dhi-roma.it/Bk"],"oriog":["http://dhi-roma.it/Bk"],"orio":["http://dhi-roma.it/Bk"],"riografia":["http://dhi-roma.it/Bk"],"riografi":["http://dhi-roma.it/Bk"],"riograf":["http://dhi-roma.it/Bk"],"riogra":["http://dhi-roma.it/Bk"],"riogr":["http://dhi-roma.it/Bk"],"riog":["http://dhi-roma.it/Bk"],"rio":["http://dhi-roma.it/Bk"],"insegnamento":["http://dhi-roma.it/Bk"],"insegnament":["http://dhi-roma.it/Bk"],"insegnamen":["http://dhi-roma.it/Bk"],"insegname":["http://dhi-roma.it/Bk"],"insegnam":["http://dhi-roma.it/Bk"],"insegna":["http://dhi-roma.it/Bk"],"insegn":["http://dhi-roma.it/Bk"],"inseg":["http://dhi-roma.it/Bk"],"inse":["http://dhi-roma.it/Bk"],"ins":["http://dhi-roma.it/Bk"],"in":["http://dhi-roma.it/Bk","http://dhi-roma.it/Ca"],"nsegnamento":["http://dhi-roma.it/Bk"],"nsegnament":["http://dhi-roma.it/Bk"],"nsegnamen":["http://dhi-roma.it/Bk"],"nsegname":["http://dhi-roma.it/Bk"],"nsegnam":["http://dhi-roma.it/Bk"],"nsegna":["http://dhi-roma.it/Bk"],"nsegn":["http://dhi-roma.it/Bk"],"nseg":["http://dhi-roma.it/Bk"],"nse":["http://dhi-roma.it/Bk"],"ns":["http://dhi-roma.it/Bk"],"n":["http://dhi-roma.it/Bk"],"segnamento":["http://dhi-roma.it/Bk"],"segnament":["http://dhi-roma.it/Bk"],"segnamen":["http://dhi-roma.it/Bk"],"segname":["http://dhi-roma.it/Bk"],"segnam":["http://dhi-roma.it/Bk"],"segna":["http://dhi-roma.it/Bk"],"segn":["http://dhi-roma.it/Bk"],"seg":["http://dhi-roma.it/Bk"],"se":["http://dhi-roma.it/Bk"],"lioteche":["http://dhi-roma.it/C","http://dhi-roma.it/Ca","http://dhi-roma.it/Cb","http://dhi-roma.it/Cc"],"liotech":["http://dhi-roma.it/C","http://dhi-roma.it/Ca","http://dhi-roma.it/Cb","http://dhi-roma.it/Cc"],"liotec":["http://dhi-roma.it/C","http://dhi-roma.it/Ca","http://dhi-roma.it/Cb","http://dhi-roma.it/Cc"],"liote":["http://dhi-roma.it/C","http://dhi-roma.it/Ca","http://dhi-roma.it/Cb","http://dhi-roma.it/Cc"],"liot":["http://dhi-roma.it/C","http://dhi-roma.it/Ca","http://dhi-roma.it/Cb","http://dhi-roma.it/Cc"],"lio":["http://dhi-roma.it/C","http://dhi-roma.it/Ca","http://dhi-roma.it/Cb","http://dhi-roma.it/Cc"],"li":["http://dhi-roma.it/C","http://dhi-roma.it/Ca","http://dhi-roma.it/Cb","http://dhi-roma.it/Cc"],"l":["http://dhi-roma.it/C","http://dhi-roma.it/Ca","http://dhi-roma.it/Cc"],"ioteche":["http://dhi-roma.it/C","http://dhi-roma.it/Cc"],"iotech":["http://dhi-roma.it/C","http://dhi-roma.it/Cc"],"iotec":["http://dhi-roma.it/C","http://dhi-roma.it/Cc"],"iote":["http://dhi-roma.it/C","http://dhi-roma.it/Cc"],"iot":["http://dhi-roma.it/C","http://dhi-roma.it/Cc"],"stituti":["http://dhi-roma.it/C"],"stitut":["http://dhi-roma.it/C"],"stitu":["http://dhi-roma.it/C"],"stit":["http://dhi-roma.it/C"],"sti":["http://dhi-roma.it/C"],"st":["http://dhi-roma.it/C"],"tituti":["http://dhi-roma.it/C"],"titut":["http://dhi-roma.it/C"],"titu":["http://dhi-roma.it/C"],"tit":["http://dhi-roma.it/C"],"ti":["http://dhi-roma.it/C"],"blioteche":["http://dhi-roma.it/Ca","http://dhi-roma.it/Cb"],"bliotech":["http://dhi-roma.it/Ca","http://dhi-roma.it/Cb"],"bliotec":["http://dhi-roma.it/Ca","http://dhi-roma.it/Cb"],"bliote":["http://dhi-roma.it/Ca","http://dhi-roma.it/Cb"],"bliot":["http://dhi-roma.it/Ca","http://dhi-roma.it/Cb"],"blio":["http://dhi-roma.it/Ca","http://dhi-roma.it/Cb"],"bli":["http://dhi-roma.it/Ca","http://dhi-roma.it/Cb"],"bl":["http://dhi-roma.it/Ca","http://dhi-roma.it/Cb"],"generale":["http://dhi-roma.it/Ca"],"general":["http://dhi-roma.it/Ca"],"genera":["http://dhi-roma.it/Ca"],"gener":["http://dhi-roma.it/Ca"],"gene":["http://dhi-roma.it/Ca"],"gen":["http://dhi-roma.it/Ca"],"ge":["http://dhi-roma.it/Ca"],"g":["http://dhi-roma.it/Ca"],"pecifiche":["http://dhi-roma.it/Cb"],"pecifich":["http://dhi-roma.it/Cb"],"pecific":["http://dhi-roma.it/Cb"],"pecifi":["http://dhi-roma.it/Cb"],"pecif":["http://dhi-roma.it/Cb"],"peci":["http://dhi-roma.it/Cb"],"pec":["http://dhi-roma.it/Cb"],"pe":["http://dhi-roma.it/Cb"],"p":["http://dhi-roma.it/Cb"],"ecifiche":["http://dhi-roma.it/Cb"],"ecifich":["http://dhi-roma.it/Cb"],"ecific":["http://dhi-roma.it/Cb"],"ecifi":["http://dhi-roma.it/Cb"],"ecif":["http://dhi-roma.it/Cb"],"eci":["http://dhi-roma.it/Cb"],"italia":["http://dhi-roma.it/Cc"],"itali":["http://dhi-roma.it/Cc"],"ital":["http://dhi-roma.it/Cc"],"ita":["http://dhi-roma.it/Cc"],"talia":["http://dhi-roma.it/Cc"],"tali":["http://dhi-roma.it/Cc"],"tal":["http://dhi-roma.it/Cc"],"ta":["http://dhi-roma.it/Cc"],"vaticano":["http://dhi-roma.it/Cc"],"vatican":["http://dhi-roma.it/Cc"],"vatica":["http://dhi-roma.it/Cc"],"vatic":["http://dhi-roma.it/Cc"],"vati":["http://dhi-roma.it/Cc"],"vat":["http://dhi-roma.it/Cc"],"va":["http://dhi-roma.it/Cc"]},{"erale":["http://dhi-roma.it/A"],"eral":["http://dhi-roma.it/A"],"era":["http://dhi-roma.it/A"],"er":["http://dhi-roma.it/A","http://dhi-roma.it/Aa"],"ici":["http://dhi-roma.it/Aa"],"eräli":["http://dhi-roma.it/Aa"],"eräl":["http://dhi-roma.it/Aa"],"erä":["http://dhi-roma.it/Aa"],"räli":["http://dhi-roma.it/Aa"],"räl":["http://dhi-roma.it/Aa"],"rä":["http://dhi-roma.it/Aa"],"r":["http://dhi-roma.it/Aa","http://dhi-roma.it/Bk"],"ografici":["http://dhi-roma.it/Aa"],"ografic":["http://dhi-roma.it/Aa"],"ografi":["http://dhi-roma.it/Aa","http://dhi-roma.it/Bk"],"ograf":["http://dhi-roma.it/Aa","http://dhi-roma.it/Bk"],"ogra":["http://dhi-roma.it/Aa","http://dhi-roma.it/Bk"],"ogr":["http://dhi-roma.it/Aa","http://dhi-roma.it/Bk"],"og":["http://dhi-roma.it/Aa","http://dhi-roma.it/Bk"],"grafici":["http://dhi-roma.it/Aa"],"grafic":["http://dhi-roma.it/Aa"],"grafi":["http://dhi-roma.it/Aa"],"graf":["http://dhi-roma.it/Aa"],"gra":["http://dhi-roma.it/Aa"],"gr":["http://dhi-roma.it/Aa"],"ie":["http://dhi-roma.it/Ac"],"tti":["http://dhi-roma.it/Ae"],"tt":["http://dhi-roma.it/Ae"],"ti":["http://dhi-roma.it/Ae"],"ore":["http://dhi-roma.it/Ae"],"or":["http://dhi-roma.it/Ae"],"d":["http://dhi-roma.it/Ae"],"di":["http://dhi-roma.it/Ae"],"iche":["http://dhi-roma.it/B"],"ich":["http://dhi-roma.it/B"],"ic":["http://dhi-roma.it/B"],"iliarie":["http://dhi-roma.it/B"],"iliari":["http://dhi-roma.it/B"],"iliar":["http://dhi-roma.it/B"],"ilia":["http://dhi-roma.it/B"],"ili":["http://dhi-roma.it/B"],"il":["http://dhi-roma.it/B"],"liarie":["http://dhi-roma.it/B"],"liari":["http://dhi-roma.it/B"],"liar":["http://dhi-roma.it/B"],"lia":["http://dhi-roma.it/B"],"li":["http://dhi-roma.it/B"],"l":["http://dhi-roma.it/B","http://dhi-roma.it/Bk"],"gistica":["http://dhi-roma.it/Bf"],"gistic":["http://dhi-roma.it/Bf"],"gisti":["http://dhi-roma.it/Bf"],"gist":["http://dhi-roma.it/Bf"],"gis":["http://dhi-roma.it/Bf"],"gi":["http://dhi-roma.it/Bf"],"g":["http://dhi-roma.it/Bf"],"ria":["http://dhi-roma.it/Bk"],"ri":["http://dhi-roma.it/Bk"],"ia":["http://dhi-roma.it/Bk"],"i":["http://dhi-roma.it/Bk"],"lla":["http://dhi-roma.it/Bk"],"ll":["http://dhi-roma.it/Bk"],"iografia":["http://dhi-roma.it/Bk"],"iografi":["http://dhi-roma.it/Bk"],"iograf":["http://dhi-roma.it/Bk"],"iogra":["http://dhi-roma.it/Bk"],"iogr":["http://dhi-roma.it/Bk"],"iog":["http://dhi-roma.it/Bk"],"io":["http://dhi-roma.it/Bk","http://dhi-roma.it/Ca","http://dhi-roma.it/Cb"],"ografia":["http://dhi-roma.it/Bk"],"egnamento":["http://dhi-roma.it/Bk"],"egnament":["http://dhi-roma.it/Bk"],"egnamen":["http://dhi-roma.it/Bk"],"egname":["http://dhi-roma.it/Bk"],"egnam":["http://dhi-roma.it/Bk"],"egna":["http://dhi-roma.it/Bk"],"egn":["http://dhi-roma.it/Bk"],"eg":["http://dhi-roma.it/Bk"],"gnamento":["http://dhi-roma.it/Bk"],"gnament":["http://dhi-roma.it/Bk"],"gnamen":["http://dhi-roma.it/Bk"],"gname":["http://dhi-roma.it/Bk"],"gnam":["http://dhi-roma.it/Bk"],"gna":["http://dhi-roma.it/Bk"],"gn":["http://dhi-roma.it/Bk"],"storico":["http://dhi-roma.it/Bk"],"storic":["http://dhi-roma.it/Bk"],"oteche":["http://dhi-roma.it/C","http://dhi-roma.it/Ca","http://dhi-roma.it/Cb","http://dhi-roma.it/Cc"],"otech":["http://dhi-roma.it/C","http://dhi-roma.it/Ca","http://dhi-roma.it/Cb","http://dhi-roma.it/Cc"],"otec":["http://dhi-roma.it/C","http://dhi-roma.it/Ca","http://dhi-roma.it/Cb","http://dhi-roma.it/Cc"],"ote":["http://dhi-roma.it/C","http://dhi-roma.it/Ca","http://dhi-roma.it/Cb","http://dhi-roma.it/Cc"],"ot":["http://dhi-roma.it/C","http://dhi-roma.it/Ca","http://dhi-roma.it/Cb","http://dhi-roma.it/Cc"],"o":["http://dhi-roma.it/C","http://dhi-roma.it/Ca","http://dhi-roma.it/Cb","http://dhi-roma.it/Cc"],"ituti":["http://dhi-roma.it/C"],"itut":["http://dhi-roma.it/C"],"itu":["http://dhi-roma.it/C"],"it":["http://dhi-roma.it/C"],"ioteche":["http://dhi-roma.it/Ca","http://dhi-roma.it/Cb"],"iotech":["http://dhi-roma.it/Ca","http://dhi-roma.it/Cb"],"iotec":["http://dhi-roma.it/Ca","http://dhi-roma.it/Cb"],"iote":["http://dhi-roma.it/Ca","http://dhi-roma.it/Cb"],"iot":["http://dhi-roma.it/Ca","http://dhi-roma.it/Cb"],"n":["http://dhi-roma.it/Ca"],"enerale":["http://dhi-roma.it/Ca"],"eneral":["http://dhi-roma.it/Ca"],"enera":["http://dhi-roma.it/Ca"],"ener":["http://dhi-roma.it/Ca"],"ene":["http://dhi-roma.it/Ca"],"en":["http://dhi-roma.it/Ca"],"nerale":["http://dhi-roma.it/Ca"],"neral":["http://dhi-roma.it/Ca"],"nera":["http://dhi-roma.it/Ca"],"ner":["http://dhi-roma.it/Ca"],"ne":["http://dhi-roma.it/Ca"],"cifiche":["http://dhi-roma.it/Cb"],"cifich":["http://dhi-roma.it/Cb"],"cific":["http://dhi-roma.it/Cb"],"cifi":["http://dhi-roma.it/Cb"],"cif":["http://dhi-roma.it/Cb"],"ci":["http://dhi-roma.it/Cb"],"teche":["http://dhi-roma.it/Cc"],"tech":["http://dhi-roma.it/Cc"],"tec":["http://dhi-roma.it/Cc"],"te":["http://dhi-roma.it/Cc"],"t":["http://dhi-roma.it/Cc"],"alia":["http://dhi-roma.it/Cc"],"ali":["http://dhi-roma.it/Cc"],"al":["http://dhi-roma.it/Cc"],"aticano":["http://dhi-roma.it/Cc"],"atican":["http://dhi-roma.it/Cc"],"atica":["http://dhi-roma.it/Cc"],"atic":["http://dhi-roma.it/Cc"],"ati":["http://dhi-roma.it/Cc"],"at":["http://dhi-roma.it/Cc"]},{"rale":["http://dhi-roma.it/A","http://dhi-roma.it/Ca"],"ral":["http://dhi-roma.it/A","http://dhi-roma.it/Ca"],"ra":["http://dhi-roma.it/A","http://dhi-roma.it/Aa","http://dhi-roma.it/Bk","http://dhi-roma.it/Ca"],"r":["http://dhi-roma.it/A"],"ale":["http://dhi-roma.it/A"],"al":["http://dhi-roma.it/A"],"a":["http://dhi-roma.it/A","http://dhi-roma.it/Aa","http://dhi-roma.it/Bk"],"äli":["http://dhi-roma.it/Aa"],"äl":["http://dhi-roma.it/Aa"],"ä":["http://dhi-roma.it/Aa"],"li":["http://dhi-roma.it/Aa"],"rafici":["http://dhi-roma.it/Aa"],"rafic":["http://dhi-roma.it/Aa"],"rafi":["http://dhi-roma.it/Aa","http://dhi-roma.it/Bk"],"raf":["http://dhi-roma.it/Aa","http://dhi-roma.it/Bk"],"afici":["http://dhi-roma.it/Aa"],"afic":["http://dhi-roma.it/Aa"],"afi":["http://dhi-roma.it/Aa"],"af":["http://dhi-roma.it/Aa"],"re":["http://dhi-roma.it/Ae"],"che":["http://dhi-roma.it/B","http://dhi-roma.it/Cc"],"ch":["http://dhi-roma.it/B"],"iarie":["http://dhi-roma.it/B"],"iari":["http://dhi-roma.it/B"],"iar":["http://dhi-roma.it/B"],"ia":["http://dhi-roma.it/B","http://dhi-roma.it/Cc"],"arie":["http://dhi-roma.it/B"],"ari":["http://dhi-roma.it/B"],"ar":["http://dhi-roma.it/B"],"istica":["http://dhi-roma.it/Bf"],"istic":["http://dhi-roma.it/Bf"],"isti":["http://dhi-roma.it/Bf"],"ist":["http://dhi-roma.it/Bf"],"is":["http://dhi-roma.it/Bf"],"stica":["http://dhi-roma.it/Bf"],"stic":["http://dhi-roma.it/Bf"],"sti":["http://dhi-roma.it/Bf"],"st":["http://dhi-roma.it/Bf"],"la":["http://dhi-roma.it/Bk"],"grafia":["http://dhi-roma.it/Bk"],"grafi":["http://dhi-roma.it/Bk"],"graf":["http://dhi-roma.it/Bk"],"gra":["http://dhi-roma.it/Bk"],"gr":["http://dhi-roma.it/Bk"],"g":["http://dhi-roma.it/Bk"],"rafia":["http://dhi-roma.it/Bk"],"namento":["http://dhi-roma.it/Bk"],"nament":["http://dhi-roma.it/Bk"],"namen":["http://dhi-roma.it/Bk"],"name":["http://dhi-roma.it/Bk"],"nam":["http://dhi-roma.it/Bk"],"na":["http://dhi-roma.it/Bk"],"amento":["http://dhi-roma.it/Bk"],"ament":["http://dhi-roma.it/Bk"],"amen":["http://dhi-roma.it/Bk"],"ame":["http://dhi-roma.it/Bk"],"am":["http://dhi-roma.it/Bk"],"torico":["http://dhi-roma.it/Bk"],"toric":["http://dhi-roma.it/Bk"],"orico":["http://dhi-roma.it/Bk"],"oric":["http://dhi-roma.it/Bk"],"teche":["http://dhi-roma.it/C","http://dhi-roma.it/Ca","http://dhi-roma.it/Cb"],"tech":["http://dhi-roma.it/C","http://dhi-roma.it/Ca","http://dhi-roma.it/Cb"],"tec":["http://dhi-roma.it/C","http://dhi-roma.it/Ca","http://dhi-roma.it/Cb"],"te":["http://dhi-roma.it/C","http://dhi-roma.it/Ca","http://dhi-roma.it/Cb"],"t":["http://dhi-roma.it/C","http://dhi-roma.it/Ca","http://dhi-roma.it/Cb"],"eche":["http://dhi-roma.it/C","http://dhi-roma.it/Ca","http://dhi-roma.it/Cb","http://dhi-roma.it/Cc"],"ech":["http://dhi-roma.it/C","http://dhi-roma.it/Ca","http://dhi-roma.it/Cb","http://dhi-roma.it/Cc"],"ec":["http://dhi-roma.it/C","http://dhi-roma.it/Ca","http://dhi-roma.it/Cb","http://dhi-roma.it/Cc"],"e":["http://dhi-roma.it/C"],"tuti":["http://dhi-roma.it/C"],"tut":["http://dhi-roma.it/C"],"tu":["http://dhi-roma.it/C"],"erale":["http://dhi-roma.it/Ca"],"eral":["http://dhi-roma.it/Ca"],"era":["http://dhi-roma.it/Ca"],"er":["http://dhi-roma.it/Ca"],"ifiche":["http://dhi-roma.it/Cb"],"ifich":["http://dhi-roma.it/Cb"],"ific":["http://dhi-roma.it/Cb"],"ifi":["http://dhi-roma.it/Cb"],"if":["http://dhi-roma.it/Cb"],"fiche":["http://dhi-roma.it/Cb"],"fich":["http://dhi-roma.it/Cb"],"fic":["http://dhi-roma.it/Cb"],"fi":["http://dhi-roma.it/Cb"],"f":["http://dhi-roma.it/Cb"],"lia":["http://dhi-roma.it/Cc"],"ticano":["http://dhi-roma.it/Cc"],"tican":["http://dhi-roma.it/Cc"],"tica":["http://dhi-roma.it/Cc"],"tic":["http://dhi-roma.it/Cc"],"ti":["http://dhi-roma.it/Cc"],"icano":["http://dhi-roma.it/Cc"],"ican":["http://dhi-roma.it/Cc"],"ica":["http://dhi-roma.it/Cc"],"ic":["http://dhi-roma.it/Cc"]},{"le":["http://dhi-roma.it/A"],"l":["http://dhi-roma.it/A"],"fici":["http://dhi-roma.it/Aa"],"fic":["http://dhi-roma.it/Aa"],"fi":["http://dhi-roma.it/Aa","http://dhi-roma.it/Bk"],"f":["http://dhi-roma.it/Aa","http://dhi-roma.it/Bk"],"he":["http://dhi-roma.it/B","http://dhi-roma.it/C","http://dhi-roma.it/Ca","http://dhi-roma.it/Cb","http://dhi-roma.it/Cc"],"h":["http://dhi-roma.it/B"],"rie":["http://dhi-roma.it/B"],"tica":["http://dhi-roma.it/Bf"],"tic":["http://dhi-roma.it/Bf"],"ti":["http://dhi-roma.it/Bf"],"t":["http://dhi-roma.it/Bf"],"afia":["http://dhi-roma.it/Bk"],"afi":["http://dhi-roma.it/Bk"],"af":["http://dhi-roma.it/Bk"],"fia":["http://dhi-roma.it/Bk"],"mento":["http://dhi-roma.it/Bk"],"ment":["http://dhi-roma.it/Bk"],"men":["http://dhi-roma.it/Bk"],"ento":["http://dhi-roma.it/Bk"],"ent":["http://dhi-roma.it/Bk"],"en":["http://dhi-roma.it/Bk"],"nto":["http://dhi-roma.it/Bk"],"nt":["http://dhi-roma.it/Bk"],"rico":["http://dhi-roma.it/Bk"],"ric":["http://dhi-roma.it/Bk"],"ico":["http://dhi-roma.it/Bk"],"ic":["http://dhi-roma.it/Bk","http://dhi-roma.it/Cb"],"che":["http://dhi-roma.it/C","http://dhi-roma.it/Ca","http://dhi-roma.it/Cb"],"uti":["http://dhi-roma.it/C"],"ut":["http://dhi-roma.it/C"],"u":["http://dhi-roma.it/C"],"ale":["http://dhi-roma.it/Ca"],"al":["http://dhi-roma.it/Ca"],"iche":["http://dhi-roma.it/Cb"],"ich":["http://dhi-roma.it/Cb"],"cano":["http://dhi-roma.it/Cc"],"can":["http://dhi-roma.it/Cc"],"ca":["http://dhi-roma.it/Cc"],"ano":["http://dhi-roma.it/Cc"],"an":["http://dhi-roma.it/Cc"]},{"co":["http://dhi-roma.it/Bk"],"c":["http://dhi-roma.it/Bk"],"le":["http://dhi-roma.it/Ca"],"no":["http://dhi-roma.it/Cc"],"n":["http://dhi-roma.it/Cc"]},{}]